README.rst
setup.py
import_wikis/__init__.py
import_wikis/management/__init__.py
import_wikis/management/commands/__init__.py
import_wikis/management/commands/find_more_mapdata.py
import_wikis/management/commands/import_mediawiki.py
import_wikis/mediawiki/__init__.py
import_wikis/mediawiki/mediawiki.py
import_wikis/mediawiki/tests.py
import_wikis/sycamore/__init__.py
import_wikis/sycamore/syc_import.py
import_wikis/sycamore/sycamore_scripts/__init__.py
import_wikis/sycamore/sycamore_scripts/export.py
import_wikis/sycamore/sycamore_scripts/user_export.py
localwiki_import_wikis.egg-info/PKG-INFO
localwiki_import_wikis.egg-info/SOURCES.txt
localwiki_import_wikis.egg-info/dependency_links.txt
localwiki_import_wikis.egg-info/requires.txt
localwiki_import_wikis.egg-info/top_level.txt