Metadata-Version: 1.0
Name: localwiki-import-wikis
Version: 0.3.3
Summary: Import legacy wiki engines into LocalWiki
Home-page: http://github.com/philipn/localwiki-import-wikis
Author: Philip Neustrom
Author-email: philipn@gmail.com
License: UNKNOWN
Platform: UNKNOWN
